django_app_permissions/__init__.py
django_app_permissions/admin.py
django_app_permissions/apps.py
django_app_permissions/models.py
django_app_permissions/tests.py
django_app_permissions/views.py
django_app_permissions/management/__init__.py
django_app_permissions/management/commands/__init__.py
django_app_permissions/management/commands/resolve_app_groups.py
django_app_permissions/middleware/__init__.py
django_app_permissions/middleware/auth.py
django_app_permissions/migrations/__init__.py
django_app_permissions-2.2.0.dist-info/LICENSE
django_app_permissions-2.2.0.dist-info/METADATA
django_app_permissions-2.2.0.dist-info/WHEEL
django_app_permissions-2.2.0.dist-info/top_level.txt
django_app_permissions-2.2.0.dist-info/RECORD
